DESCRIPTION.rst
MANIFEST.in
setup.py
socketextra/__init__.py
socketextra/_socketextra.c
socketextra.egg-info/PKG-INFO
socketextra.egg-info/SOURCES.txt
socketextra.egg-info/dependency_links.txt
socketextra.egg-info/top_level.txt